amaas/__init__.py
amaas/_version.py
amaas/grpc/__init__.py
amaas/grpc/aio/__init__.py
amaas/grpc/exception/__init__.py
amaas/grpc/protos/scan_pb2.py
amaas/grpc/protos/scan_pb2.pyi
amaas/grpc/protos/scan_pb2_grpc.py
cloudone_vsapi-1.0.4.dist-info/LICENSE
cloudone_vsapi-1.0.4.dist-info/METADATA
cloudone_vsapi-1.0.4.dist-info/NOTICE
cloudone_vsapi-1.0.4.dist-info/WHEEL
cloudone_vsapi-1.0.4.dist-info/top_level.txt
cloudone_vsapi-1.0.4.dist-info/RECORD
