Metadata-Version: 2.1
Name: cloudone-vsapi
Version: 1.0.4
Summary: Trend Micro Cloud One VSAPI SDK for python
Home-page: https://github.com/trendmicro/cloudone-antimalware-python-sdk
Author: Trend Micro Cloud One Team
Classifier: Programming Language :: Python
Classifier: Programming Language :: Python :: 3
Classifier: Programming Language :: Python :: 3.7
Classifier: Programming Language :: Python :: 3.8
Classifier: Programming Language :: Python :: 3.9
Classifier: Programming Language :: Python :: 3.10
Classifier: Programming Language :: Python :: 3.11
Classifier: License :: OSI Approved :: MIT License
Requires-Python: >=3.7
License-File: LICENSE
License-File: NOTICE
Requires-Dist: grpcio (==1.51.3)
Requires-Dist: protobuf (==4.22.0)
